LICENSE
MANIFEST.in
README.md
setup.py
djangular/.DS_Store
djangular/__init__.py
djangular/finders.py
djangular/middleware.py
djangular/models.py
djangular/storage.py
djangular/urls.py
djangular/utils.py
djangular/views.py
djangular.egg-info/PKG-INFO
djangular.egg-info/SOURCES.txt
djangular.egg-info/dependency_links.txt
djangular.egg-info/top_level.txt
djangular/config/angularapp_template/__init__.py
djangular/config/angularapp_template/models.py
djangular/config/angularapp_template/views.py
djangular/config/angularapp_template/app/index.html
djangular/config/angularapp_template/app/css/app.css
djangular/config/angularapp_template/app/js/app.js
djangular/config/angularapp_template/app/js/controllers.js
djangular/config/angularapp_template/app/js/directives.js
djangular/config/angularapp_template/app/js/filters.js
djangular/config/angularapp_template/app/js/services.js
djangular/config/angularapp_template/app/partials/partial1.html
djangular/config/angularapp_template/app/partials/partial2.html
djangular/config/angularapp_template/tests/__init__.py
djangular/config/angularapp_template/tests/simple.py
djangular/config/angularapp_template/tests/e2e/runner.html
djangular/config/angularapp_template/tests/e2e/scenarios.js
djangular/config/angularapp_template/tests/unit/controllersSpec.js
djangular/config/angularapp_template/tests/unit/directivesSpec.js
djangular/config/angularapp_template/tests/unit/filtersSpec.js
djangular/config/angularapp_template/tests/unit/servicesSpec.js
djangular/config/angularsite_template/templates/karma-e2e.conf.js
djangular/config/angularsite_template/templates/karma-unit.conf.js
djangular/management/__init__.py
djangular/management/commands/__init__.py
djangular/management/commands/makeangularsite.py
djangular/management/commands/runtestserver.py
djangular/management/commands/startangularapp.py
djangular/management/commands/testjs.py
djangular/static/.DS_Store
djangular/static/js/resource_patch.js
djangular/static/lib/.DS_Store
djangular/static/lib/angular/angular-animate.js
djangular/static/lib/angular/angular-animate.min.js
