Metadata-Version: 1.0
Name: djangular
Version: 0.2.7
Summary: A reusable app that provides better app integration with AngularJS.
Home-page: http://github.com/appliedsec/djangular
Author: Brian Montgomery
Author-email: brianm@appliedsec.com
License: Apache
Keywords: djangular django angular angularjs
Platform: UNKNOWN
Classifier: Intended Audience :: Developers
Classifier: License :: OSI Approved :: Apache Software License
Classifier: Programming Language :: Python :: 2.7
Classifier: Operating System :: OS Independent
Classifier: Topic :: Internet :: WWW/HTTP
Classifier: Topic :: Internet :: WWW/HTTP :: Dynamic Content
Classifier: Topic :: Software Development :: Libraries :: Python Modules
